topt/__init__.py
topt/converter.py
topt/converter_test.py
topt/optimizer.py
topt/optimizer_test.py
topt/py.typed
topt-0.0.3.dist-info/LICENSE
topt-0.0.3.dist-info/METADATA
topt-0.0.3.dist-info/WHEEL
topt-0.0.3.dist-info/RECORD
